pyroom/__init__.py
pyroom/catalog.py
pyroom/image.py
pyroom-0.0.1.dist-info/DESCRIPTION.rst
pyroom-0.0.1.dist-info/METADATA
pyroom-0.0.1.dist-info/RECORD
pyroom-0.0.1.dist-info/WHEEL
pyroom-0.0.1.dist-info/metadata.json
pyroom-0.0.1.dist-info/top_level.txt
