Metadata-Version: 2.0
Name: pyroom
Version: 0.0.1
Summary: Quick & dirty Adobe Lightroom catalog manager
Home-page: https://github.com/Dalloriam/pyroom
Author: Dalloriam
Author-email: UNKNOWN
License: MIT
Platform: UNKNOWN
